mypythonlib/__init__.py
mypythonlib/myfunctions.py
tests/__init__.py
tests/test_myfunctions.py
new_package_name-0.1.0.dist-info/METADATA
new_package_name-0.1.0.dist-info/WHEEL
new_package_name-0.1.0.dist-info/top_level.txt
new_package_name-0.1.0.dist-info/RECORD
